{
  "cookies": [
    {
      "name": "grafana_session",
      "value": "73ea2c06e30dc9fbaaabd0c749f23b47",
      "domain": "localhost",
      "path": "/",
      "expires": 1713708626.578,
      "httpOnly": true,
      "secure": false,
      "sameSite": "Lax"
    },
    {
      "name": "grafana_session_expiry",
      "value": "1711117221",
      "domain": "localhost",
      "path": "/",
      "expires": 1713708626.578,
      "httpOnly": false,
      "secure": false,
      "sameSite": "Lax"
    }
  ],
  "origins": []
}